{
  "version": "1.0",
  "defaultProvider": "jsdelivr",
  "libraries": [
    {
      "library": "bootstrap@4.4.1",
      "destination": "wwwroot\\lib\\bootstrap",
      "files": [
        "dist/css/bootstrap.min.css"
      ]
    },
    {
      "library": "ThemesGuide/top-hat@2274176073d2e4783c78df080c6c3396e2abc2b4",
      "destination": "wwwroot\\lib\\ThemesGuide/top-hat",
      "files": [
        "dist/graymor/theme.min.css"
      ]
    },
    {
      "library": "@fortawesome/fontawesome-free@5.12.0",
      "destination": "wwwroot\\lib\\@fortawesome/fontawesome-free",
      "files": [
        "css/all.min.css",
        "webfonts/fa-brands-400.eot",
        "webfonts/fa-brands-400.svg",
        "webfonts/fa-brands-400.ttf",
        "webfonts/fa-brands-400.woff",
        "webfonts/fa-brands-400.woff2",
        "webfonts/fa-regular-400.eot",
        "webfonts/fa-regular-400.svg",
        "webfonts/fa-regular-400.ttf",
        "webfonts/fa-regular-400.woff",
        "webfonts/fa-regular-400.woff2",
        "webfonts/fa-solid-900.eot",
        "webfonts/fa-solid-900.svg",
        "webfonts/fa-solid-900.ttf",
        "webfonts/fa-solid-900.woff",
        "webfonts/fa-solid-900.woff2"
      ]
    }
  ]
}